MANIFEST.in
info.py
setup.py
jupyter_gauche/__init__.py
jupyter_gauche/__main__.py
jupyter_gauche/install.py
jupyter_gauche/kernel.py
jupyter_gauche.egg-info/PKG-INFO
jupyter_gauche.egg-info/SOURCES.txt
jupyter_gauche.egg-info/dependency_links.txt
jupyter_gauche.egg-info/entry_points.txt
jupyter_gauche.egg-info/requires.txt
jupyter_gauche.egg-info/top_level.txt
t/__init__.py
t/kernel.py