Metadata-Version: 1.0
Name: jupyter-gauche
Version: 0.0.4
Summary: Gauche Kernel for Jupyter Notebook
Home-page: http://arata.hatenadiary.com
Author: ara_ta3
Author-email: tarata43@yahoo.co.jp
License: UNKNOWN
Platform: UNKNOWN
